scat/__init__.py
scat/__main__.py
scat/main.py
scat/util.py
scat/iodevices/__init__.py
scat/iodevices/abstractio.py
scat/iodevices/fileio.py
scat/iodevices/serialio.py
scat/iodevices/usbio.py
scat/parsers/__init__.py
scat/parsers/abstractparser.py
scat/parsers/hisilicon/__init__.py
scat/parsers/hisilicon/hisiliconparser.py
scat/parsers/hisilicon/hisilogparser.py
scat/parsers/hisilicon/hisinestedparser.py
scat/parsers/qualcomm/__init__.py
scat/parsers/qualcomm/diag1xlogparser.py
scat/parsers/qualcomm/diagcmd.py
scat/parsers/qualcomm/diagcommoneventparser.py
scat/parsers/qualcomm/diagfallbackeventparser.py
scat/parsers/qualcomm/diaggsmeventparser.py
scat/parsers/qualcomm/diaggsmlogparser.py
scat/parsers/qualcomm/diaglteeventparser.py
scat/parsers/qualcomm/diagltelogparser.py
scat/parsers/qualcomm/diagnrlogparser.py
scat/parsers/qualcomm/diagumtslogparser.py
scat/parsers/qualcomm/diagwcdmalogparser.py
scat/parsers/qualcomm/qualcommparser.py
scat/parsers/samsung/__init__.py
scat/parsers/samsung/samsungparser.py
scat/parsers/samsung/sdmcmd.py
scat/parsers/samsung/sdmcommonparser.py
scat/parsers/samsung/sdmcontrolparser.py
scat/parsers/samsung/sdmedgeparser.py
scat/parsers/samsung/sdmhspaparser.py
scat/parsers/samsung/sdmipparser.py
scat/parsers/samsung/sdmlteparser.py
scat/parsers/samsung/sdmtraceparser.py
scat/parsers/unisoc/__init__.py
scat/parsers/unisoc/unisocparser.py
scat/writers/__init__.py
scat/writers/abstractwriter.py
scat/writers/pcapwriter.py
scat/writers/rawwriter.py
scat/writers/socketwriter.py
signalcat-2.0.0.dist-info/METADATA
signalcat-2.0.0.dist-info/WHEEL
signalcat-2.0.0.dist-info/entry_points.txt
signalcat-2.0.0.dist-info/licenses/COPYING
signalcat-2.0.0.dist-info/RECORD
