Metadata-Version: 2.4
Name: signalcat
Version: 2.0.0
Summary: Signaling Collection and Analysis Tool
Project-URL: Homepage, https://github.com/fgsect/scat
Project-URL: Bug Tracker, https://github.com/fgsect/scat/issues
Author-email: Shinjo Park <peremen@gmail.com>
License: GPL-2.0-or-later
License-File: COPYING
Classifier: Operating System :: OS Independent
Requires-Python: >=3.10
Requires-Dist: bitstring>=4.0
Requires-Dist: packaging>=19.0
Requires-Dist: pyserial>=3.3
Requires-Dist: pyusb>=1.0.2
Provides-Extra: fastcrc
Requires-Dist: libscrc>=1.8.0; extra == 'fastcrc'
